recentearthquake/__init__.py
earthquake_indonesia_bmkg_2023-0.2.dist-info/LICENSE
earthquake_indonesia_bmkg_2023-0.2.dist-info/METADATA
earthquake_indonesia_bmkg_2023-0.2.dist-info/WHEEL
earthquake_indonesia_bmkg_2023-0.2.dist-info/top_level.txt
earthquake_indonesia_bmkg_2023-0.2.dist-info/RECORD
