Metadata-Version: 2.1
Name: earthquake-indonesia-bmkg-2023
Version: 0.2
Summary: This package provides the latest earthquake data in Indonesia from BMKG
Home-page: https://github.com/faris-r/earthquake-bmkg
Author: Rendra Faris
Author-email: farisrendra@gmail.com
Classifier: Programming Language :: Python :: 3
Classifier: License :: OSI Approved :: GNU General Public License v3 (GPLv3)
Classifier: Operating System :: OS Independent
Classifier: Development Status :: 5 - Production/Stable
Requires-Python: >=3.6
License-File: LICENSE
